[{"id": 42777, "name": "Berane Airport", "type": "small_airport", "coord": [42.8390007019043, 19.8619995117188], "code": "IVG", "country": 114, "prefecture": 1729, "city": 28869, "name_ko": "Berane 공항"}, {"id": 4613, "name": "Podgorica Airport / Podgorica Golubovci Airbase", "type": "large_airport", "coord": [42.359402, 19.2519], "code": "TGD", "country": 114, "prefecture": 1730, "city": 28870, "name_ko": "Podgorica 공항 / Podgorica Golubovci Airbase"}, {"id": 4615, "name": "Tivat Airport", "type": "medium_airport", "coord": [42.4047012329102, 18.7233009338379], "code": "TIV", "country": 114, "prefecture": 1742, "city": -1, "name_ko": "Tivat 공항"}]