[{"id": 3151, "name": "Aristides Pereira International Airport", "type": "large_airport", "coord": [16.136499, -22.888901], "code": "BVC", "country": 36, "prefecture": 560, "city": 14314, "name_ko": "Aristides Pereira 국제공항"}, {"id": 3152, "name": "Maio Airport", "type": "medium_airport", "coord": [15.1559000015259, -23.2136993408203], "code": "MMO", "country": 36, "prefecture": 562, "city": 14306, "name_ko": "Maio 공항"}, {"id": 31961, "name": "Mosteiros Airport", "type": "small_airport", "coord": [15.045, -24.339199], "code": "MTI", "country": 36, "prefecture": 570, "city": 14308, "name_ko": "Mosteiros 공항"}, {"id": 31560, "name": "Agostinho Neto Airport", "type": "small_airport", "coord": [17.2028007507324, -25.0905990600586], "code": "NTO", "country": 36, "prefecture": 568, "city": 14309, "name_ko": "Agostinho Neto 공항"}, {"id": 3153, "name": "Nelson Mandela International Airport", "type": "large_airport", "coord": [14.941126, -23.484728], "code": "RAI", "country": 36, "prefecture": 580, "city": 14327, "name_ko": "Nelson Mandela 국제공항"}, {"id": 32287, "name": "São Filipe Airport", "type": "small_airport", "coord": [14.8850002289, -24.4799995422], "code": "SFL", "country": 36, "prefecture": 572, "city": 14304, "name_ko": "São Filipe 공항"}, {"id": 3150, "name": "Amílcar Cabral International Airport", "type": "large_airport", "coord": [16.7414, -22.9494], "code": "SID", "country": 36, "prefecture": 563, "city": 14307, "name_ko": "Amílcar Cabral 국제공항"}, {"id": 3154, "name": "Preguiça Airport", "type": "medium_airport", "coord": [16.588852, -24.284132], "code": "SNE", "country": 36, "prefecture": 565, "city": -1, "name_ko": "Preguiça 공항"}, {"id": 3155, "name": "Cesaria Evora International Airport", "type": "large_airport", "coord": [16.833363, -25.055308], "code": "VXE", "country": 36, "prefecture": 564, "city": 14334, "name_ko": "Cesaria Evora 국제공항"}]