[{"id": 26525, "name": "Barisal Airport", "type": "medium_airport", "coord": [22.801001, 90.301201], "code": "BZL", "country": 192, "prefecture": 3098, "city": 47541, "name_ko": "Barisal 공항"}, {"id": 26527, "name": "Shah Amanat International Airport", "type": "large_airport", "coord": [22.249599, 91.813301], "code": "CGP", "country": 192, "prefecture": 3091, "city": 47546, "name_ko": "Shah Amanat 국제공항"}, {"id": 30832, "name": "Comilla Airport", "type": "small_airport", "coord": [23.440133, 91.188685], "code": "CLA", "country": 192, "prefecture": 3091, "city": 47548, "name_ko": "Comilla 공항"}, {"id": 26526, "name": "Cox's Bazar Airport", "type": "medium_airport", "coord": [21.457517, 91.963263], "code": "CXB", "country": 192, "prefecture": 3091, "city": 47549, "name_ko": "Cox's Bazar 공항"}, {"id": 26534, "name": "Hazrat Shahjalal International Airport", "type": "large_airport", "coord": [23.843347, 90.397783], "code": "DAC", "country": 192, "prefecture": 3092, "city": 47550, "name_ko": "Hazrat Shahjalal 국제공항"}, {"id": 26528, "name": "Ishurdi Airport", "type": "medium_airport", "coord": [24.1525, 89.0494], "code": "IRD", "country": 192, "prefecture": 3094, "city": 47581, "name_ko": "Ishurdi 공항"}, {"id": 26529, "name": "Jessore Airport", "type": "medium_airport", "coord": [23.1838, 89.160797], "code": "JSR", "country": 192, "prefecture": 3097, "city": 47559, "name_ko": "Jessore 공항"}, {"id": 26530, "name": "Shah Makhdum Airport", "type": "medium_airport", "coord": [24.437201, 88.616501], "code": "RJH", "country": 192, "prefecture": 3094, "city": 47591, "name_ko": "Shah Makhdum 공항"}, {"id": 26531, "name": "Saidpur Airport", "type": "medium_airport", "coord": [25.759199, 88.908897], "code": "SPD", "country": 192, "prefecture": 3095, "city": 47584, "name_ko": "Saidpur 공항"}, {"id": 32455, "name": "Thakurgaon Airport", "type": "small_airport", "coord": [26.016378, 88.402092], "code": "TKR", "country": 192, "prefecture": 3095, "city": 47601, "name_ko": "Thakurgaon 공항"}, {"id": 32744, "name": "Shamshernagar Airport", "type": "small_airport", "coord": [24.398333, 91.916944], "code": "ZHM", "country": 192, "prefecture": 3096, "city": 47573, "name_ko": "Shamshernagar 공항"}, {"id": 26532, "name": "Osmany International Airport", "type": "large_airport", "coord": [24.963071, 91.866903], "code": "ZYL", "country": 192, "prefecture": 3096, "city": 47599, "name_ko": "Osmany 국제공항"}]